authors/__init__.py
authors/authors.py
authors/cli.py
authors/crowd.png
authors/latex_pdf_utils.py
authors/utils.py
authors/data/all_known_authors.yml
authors/journals/AandA.py
authors/journals/MNRAS.py
authors-0.5.dist-info/licenses/LICENSE
authors-0.5.dist-info/METADATA
authors-0.5.dist-info/WHEEL
authors-0.5.dist-info/entry_points.txt
authors-0.5.dist-info/top_level.txt
authors-0.5.dist-info/RECORD
