Metadata-Version: 2.4
Name: authors
Version: 0.5
Summary: Authors of your next scientific article
Author-email: João Faria <joao.faria@unige.ch>
License: MIT
Project-URL: Repository, https://github.com/j-faria/authors
Keywords: science,journals,authors,astronomy
Classifier: Programming Language :: Python :: 3
Requires-Python: >=3.8
License-File: LICENSE
Requires-Dist: pyaml
Dynamic: license-file
